fourbyfour/__init__.py
fourbyfour/client.py
fourbyfour/errors.py
fourbyfour/http.py
fourbyfour/py.typed
fourbyfour/hooks/__init__.py
fourbyfour/hooks/hooks.py
fourbyfour/hooks/types.py
fourbyfour/notifications/__init__.py
fourbyfour/notifications/notifications.py
fourbyfour/notifications/types.py
fourbyfour/stream/__init__.py
fourbyfour/stream/topics.py
fourbyfour/stream/types.py
fourbyfour-0.1.0.dist-info/METADATA
fourbyfour-0.1.0.dist-info/WHEEL
fourbyfour-0.1.0.dist-info/RECORD
